easyjson2json/__init__.py
easyjson2json/helpers.py
easyjson2json/json2json.py
tests/__init__.py
tests/json2json_test.py
easy_json2json-0.0.2.dist-info/LICENSE
easy_json2json-0.0.2.dist-info/METADATA
easy_json2json-0.0.2.dist-info/WHEEL
easy_json2json-0.0.2.dist-info/top_level.txt
easy_json2json-0.0.2.dist-info/RECORD
