Metadata-Version: 2.1
Name: easy-json2json
Version: 0.0.2
Summary: A package for easy json parse.
Home-page: https://github.com/brworkit/python-package-easy-json2json.git
Author: brworkit
Author-email: brworkit@gmail.com
License: UNKNOWN
Download-URL: https://github.com/brworkit/python-package-easy-json2json/archive/v0.0.2.tar.gz
Platform: UNKNOWN
Classifier: Programming Language :: Python :: 3
Classifier: License :: OSI Approved :: MIT License
Classifier: Operating System :: OS Independent
Requires-Python: >=3.6
